{
	"CSSVars": {
		"--grey": "--background-neutral-moderate",
		"--grey-light": "--background-neutral-subtle",
		"--grey-lighter": "--background-neutral-minimal",
		"--grey-dark": "--border-default",
		"--grey-darker": "--text-default-default",

		"--info": "--background-info-default",
		"--info-light": "--background-info-minimal",
		"--info-dark": "--background-info-moderate",
		"--info-alt": "--background-info-subtle",

		"--danger": "--background-danger-default",
		"--warning": "--background-warning-default",
		"--success": "--background-success-default",

		"--brand": "--background-primary-default",
		"--brand-light": "--background-primary-minimal",
		"--pink": "--background-info-default",

		"--rgb-grey": "--background-neutral-default",
		"--rgb-grey-light": "--background-neutral-minimal",
		"--rgb-grey-dark": "--background-neutral-moderate",
		"--rgb-grey-lighter": "--background-neutral-subtle",
		"--rgb-grey-darker": "--text-default-default",

		"--rgb-info": "--background-info-default",
		"--rgb-info-light": "--background-info-minimal",
		"--rgb-info-dark": "--background-info-moderate",
		"--rgb-danger": "--background-danger-default",
		"--rgb-danger-alt": "--background-danger-subtle",
		"--rgb-danger-dark": "--background-danger-moderate",
		"--rgb-danger-light": "--background-danger-minimal",
		"--rgb-warning": "--background-warning-default",
		"--rgb-warning-alt": "--background-warning-subtle",
		"--rgb-warning-dark": "--background-warning-moderate",
		"--rgb-warning-light": "--background-warning-minimal",
		"--rgb-success": "--background-success-default",
		"--rgb-success-alt": "--background-success-subtle",
		"--rgb-success-dark": "--background-success-moderate",
		"--rgb-success-light": "--background-success-minimal",
		"--rgb-brand": "--background-primary-default",
		"--rgb-brand-alt": "--background-primary-subtle",
		"--rgb-brand-dark": "--background-primary-moderate",
		"--rgb-brand-light": "--background-primary-minimal",
		"--rgb-pink": "--background-info-default",
		"--rgb-pink-alt": "--background-info-subtle",
		"--rgb-pink-dark": "--background-info-moderate",
		"--rgb-pink-light": "--background-info-minimal",

		"--inverse": "--text-default-inverted",

		"--radius-btn": "--radius-4",
		"--radius-label": "--radius-4",
		"--radius-alert": "--radius-4",
		"--radius-notif": "--radius-4",
		"--radius-upload": "--radius-4",
		"--radius-input": "--radius-4",
		"--radius-input-range": "--radius-8",
		"--radius-card": "--radius-8",
		"--radius-sticker": "--radius-8",
		"--radius-popover": "--radius-8",
		"--radius-modal": "--radius-18",
		"--radius-aside": "--radius-18",

		"--space-xs": "--spacing-8",
		"--space-sm": "--spacing-16",
		"--space-md": "--spacing-32",
		"--space-lg": "--spacing-48",
		"--space-xl": "--spacing-72",

		"--fluid-5px": "--space-xs",
		"--fluid-8px": "--space-sm",
		"--fluid-10px": "--space-sm",
		"--fluid-12px": "--space-md",
		"--fluid-15px": "--space-md",
		"--fluid-18px": "--space-lg",
		"--fluid-20px": "--space-lg",
		"--fluid-25px": "--space-lg",
		"--fluid-30px": "--space-lg",
		"--fluid-35px": "--space-lg",
		"--fluid-40px": "--space-lg",
		"--fluid-45px": "--space-lg",
		"--fluid-60px": "--space-lg",

		"--font-family": "--font-family",
		"--font-weight-default": "--typography-weight-regular",
		"--font-weight-title": "--typography-weight-semibold",
		"--font-weight-page-title": "--typography-weight-bold",
		"--font-weight-page-subtitle": "--typography-weight-medium",
		"--font-weight-section-title": "--typography-weight-semibold",
		"--font-weight-section-subtitle": "--typography-weight-medium",
		"--size-default": "--typography-size-base",

		"--base": "--background-neutral-default",
		"--color": "--text-default-default",
		"--c-bg": "--background-neutral-default"
	},

	"Classes": {}
}
